google_bazaar_payment/__init__.py
google_bazaar_payment/admin.py
google_bazaar_payment/apps.py
google_bazaar_payment/models.py
google_bazaar_payment/tests.py
google_bazaar_payment/views.py
google_bazaar_payment/migrations/0001_initial.py
google_bazaar_payment/migrations/__init__.py
google_bazaar_payment/payment/__init__.py
google_bazaar_payment/payment/google_bazaar_payment.py
google_bazaar_payment/payment/payment_data.py
google_bazaar_payment/payment/utils.py
django_google_bazaar_payment-1.2.dist-info/LICENSE
django_google_bazaar_payment-1.2.dist-info/METADATA
django_google_bazaar_payment-1.2.dist-info/WHEEL
django_google_bazaar_payment-1.2.dist-info/top_level.txt
django_google_bazaar_payment-1.2.dist-info/RECORD
