Metadata-Version: 2.1
Name: django-google-bazaar-payment
Version: 1.2
Summary: This Django app created for check response token that taken from Google Play or Bazaar is valid or not . and choice with method you want to confirm your purchase with that.
Home-page: https://github.com/Milimarty/GooglePlayBazaarIn-app.git
Author: MiladNalbandi
Author-email: milimarty.mm@gmail.com
License: APACHE LICENSE, VERSION 2.0
Platform: UNKNOWN
Classifier: Environment :: Web Environment
Classifier: Framework :: Django
Classifier: Framework :: Django :: 2.2
Classifier: Intended Audience :: Developers
Classifier: License :: OSI Approved :: BSD License
Classifier: Operating System :: OS Independent
Classifier: Programming Language :: Python
Classifier: Programming Language :: Python :: 3
Classifier: Programming Language :: Python :: 3 :: Only
Classifier: Programming Language :: Python :: 3.6
Classifier: Programming Language :: Python :: 3.7
Classifier: Programming Language :: Python :: 3.8
Classifier: Topic :: Internet :: WWW/HTTP
Classifier: Topic :: Internet :: WWW/HTTP :: Dynamic Content
